mkdocs_terraform_monorepo_plugin/__init__.py
mkdocs_terraform_monorepo_plugin/merger.py
mkdocs_terraform_monorepo_plugin/parser.py
mkdocs_terraform_monorepo_plugin/plugin.py
mkdocs_terraform_monorepo_plugin-0.1.3.dist-info/LICENSE.md
mkdocs_terraform_monorepo_plugin-0.1.3.dist-info/METADATA
mkdocs_terraform_monorepo_plugin-0.1.3.dist-info/WHEEL
mkdocs_terraform_monorepo_plugin-0.1.3.dist-info/entry_points.txt
mkdocs_terraform_monorepo_plugin-0.1.3.dist-info/top_level.txt
mkdocs_terraform_monorepo_plugin-0.1.3.dist-info/RECORD
