Metadata-Version: 2.1
Name: mkdocs-terraform-monorepo-plugin
Version: 0.1.3
Summary: Plugin for adding doc tree for terraform monorepos.
Home-page: https://github.com/wtc-cloud-eng/mkdocs-terraform-monorepo-plugin
Author: Richard Wittrick
Author-email: richard.wittrick@wundermanthompson.com
License: Apache-2.0
Keywords: mkdocs terraform monorepo plugin
Platform: UNKNOWN
Classifier: Development Status :: 4 - Beta
Classifier: Intended Audience :: Developers
Classifier: Intended Audience :: Information Technology
Classifier: Programming Language :: Python
Classifier: Programming Language :: Python :: 3 :: Only
Classifier: Programming Language :: Python :: 3.6
Classifier: Programming Language :: Python :: 3.7
Requires-Python: >=3
Requires-Dist: mkdocs (>=1.1.1)
